MANIFEST.in
README
setup.cfg
setup.py
datetime2/__init__.py
datetime2/version.py
python_datetime2.egg-info/PKG-INFO
python_datetime2.egg-info/SOURCES.txt
python_datetime2.egg-info/dependency_links.txt
python_datetime2.egg-info/not-zip-safe
python_datetime2.egg-info/requires.txt
python_datetime2.egg-info/top_level.txt