Metadata-Version: 1.1
Name: python-datetime2
Version: 0.0.1
Summary: Python3 Date&Time Best Practices
Home-page: https://github.com/laco/python-datetime2/
Author: László Andrási
Author-email: mail@laszloandrasi.com
License: Apache2.0
Download-URL: https://github.com/laco/python-datetime2/tarball/0.0.1
Platform: any
Classifier: Development Status :: 4 - Beta
Classifier: Environment :: Web Environment
Classifier: Intended Audience :: Developers
Classifier: License :: OSI Approved :: BSD License
Classifier: Operating System :: OS Independent
Classifier: Programming Language :: Python
Classifier: Programming Language :: Python :: 3
Classifier: Topic :: Software Development :: Libraries :: Python Modules
